{
  "category": "enhancement",
  "description": "## Parent Task Context (Already Completed)\n\n> **Note:** The following parent task has already been completed. This context is provided to help you understand the background and requirements for this sub-task. Do not re-implement the parent task - focus only on the new sub-task described below.\n\n### layou\n\n**Description:** Redesign Application UI to Match Apple Liquid Glass 2026 Aesthetic\n\nCompletely overhaul the application interface to replicate Apple's Liquid Glass design system (2026 iteration), featuring glassmorphism, fluid animations, and depth-based layering.\n\nTechnical Implementation:\n- Design System: Implement CSS-in-JS or Tailwind CSS custom theme matching Liquid Glass specifications\n- Glassmorphism Effects: backdrop-filter with blur (20-40px), transparency layers (rgba with 0.6-0.9 alpha), subtle borders (1px rgba white/black)\n- Color Palette: Extract and replicate Apple's 2026 palette (neutral grays, vibrant accent colors, adaptive light/dark modes)\n- Typography: San Francisco Pro Display/Text font stack with appropriate weights (300-700)\n- Animations: Framer Motion or React Spring for fluid transitions (300-600ms cubic-bezier easing)\n- Depth System: Z-index hierarchy with floating cards, elevated surfaces, shadow layers (0-64px blur)\n\nUI Components to Rebuild:\n- Navigation: Translucent top bar with blur effect, floating sidebar with depth\n- Cards: Rounded corners (12-20px), glass background, subtle shadows\n- Buttons: Pill-shaped with glass effect, hover states with luminosity changes\n- Modals: Center-floating with animated backdrop blur\n- Forms: Floating labels, glass input fields with focus glow\n- Lists/Tables: Alternating transparency, hover lift animations\n\nVisual Effects:\n- Parallax scrolling for depth perception\n- Micro-interactions on all interactive elements (scale, glow, elevation changes)\n- Smooth page transitions with shared element animations\n- Dynamic light source simulation (pseudo-elements for highlights)\n- Gradient overlays with noise texture for organic feel\n\nPerformance Optimizations:\n- Use CSS containment for animation layers\n- GPU acceleration via transform3d and will-change\n- Lazy load animation libraries\n- Optimize backdrop-filter usage (known performance cost)\n- Implement reduced motion media queries for accessibility\n\nResponsive Design:\n- Breakpoints: Mobile (< 768px), Tablet (768-1024px), Desktop (> 1024px)\n- Adapt glass intensity based on screen size\n- Simplified effects on mobile for performance\n\nBrowser Compatibility:\n- Fallbacks for backdrop-filter (solid backgrounds with opacity)\n- Prefixed CSS properties (-webkit-backdrop-filter)\n- Polyfills for older browsers or graceful degradation\n\nAssets Required:\n- Reference screenshots/videos from Apple Liquid Glass 2026 design\n- Icon set matching Apple SF Symbols style\n- High-resolution background images/gradients\n- Noise textures for glass effect authenticity\n\nTesting:\n- Visual regression testing across browsers\n- Performance metrics (FPS, paint times)\n- Accessibility audit (contrast ratios with transparency)\n- Dark mode parity verification\n\n---\n\n## Task Description\n\nCreate Dashboard with Liquid Glass 2026 Design Aesthetic\n\nRedesign the dashboard interface to match the \"Liquid Glass 2026\" visual design style, featuring modern glassmorphism effects, fluid animations, and contemporary UI patterns.\n\nRequirements:\n- Research and identify the specific Liquid Glass 2026 design characteristics (frosted glass effects, translucent layers, depth shadows, blur effects)\n- Update color scheme to match Liquid Glass 2026 palette (typically featuring soft gradients, semi-transparent backgrounds, light borders)\n- Implement glassmorphism CSS properties: backdrop-filter, background blur, opacity layers, and subtle borders\n- Add smooth, fluid animations and transitions between states\n- Update typography to match the modern, clean aesthetic of Liquid Glass 2026\n- Ensure component spacing, padding, and layout proportions align with the reference design\n- Maintain or improve accessibility standards (sufficient contrast despite transparency effects)\n- Verify responsive behavior across different screen sizes\n- Test performance impact of visual effects and optimize if necessary\n\nVisual Elements to Include:\n- Frosted glass card containers with blur effects\n- Floating elements with subtle drop shadows\n- Gradient overlays and color transitions\n- Smooth hover and interaction animations\n- Modern iconography consistent with the design language",
  "title": "dahsboard",
  "images": [],
  "imagePaths": [],
  "textFilePaths": [],
  "skipTests": false,
  "model": "opus",
  "thinkingLevel": "none",
  "reasoningEffort": "none",
  "priority": 2,
  "planningMode": "skip",
  "requirePlanApproval": false,
  "dependencies": [
    "feature-1768631509599-99aevgkw2"
  ],
  "workMode": "current",
  "titleGenerating": false,
  "status": "verified",
  "id": "feature-1768659397678-p58fxm3e9",
  "descriptionHistory": [
    {
      "description": "## Parent Task Context (Already Completed)\n\n> **Note:** The following parent task has already been completed. This context is provided to help you understand the background and requirements for this sub-task. Do not re-implement the parent task - focus only on the new sub-task described below.\n\n### layou\n\n**Description:** Redesign Application UI to Match Apple Liquid Glass 2026 Aesthetic\n\nCompletely overhaul the application interface to replicate Apple's Liquid Glass design system (2026 iteration), featuring glassmorphism, fluid animations, and depth-based layering.\n\nTechnical Implementation:\n- Design System: Implement CSS-in-JS or Tailwind CSS custom theme matching Liquid Glass specifications\n- Glassmorphism Effects: backdrop-filter with blur (20-40px), transparency layers (rgba with 0.6-0.9 alpha), subtle borders (1px rgba white/black)\n- Color Palette: Extract and replicate Apple's 2026 palette (neutral grays, vibrant accent colors, adaptive light/dark modes)\n- Typography: San Francisco Pro Display/Text font stack with appropriate weights (300-700)\n- Animations: Framer Motion or React Spring for fluid transitions (300-600ms cubic-bezier easing)\n- Depth System: Z-index hierarchy with floating cards, elevated surfaces, shadow layers (0-64px blur)\n\nUI Components to Rebuild:\n- Navigation: Translucent top bar with blur effect, floating sidebar with depth\n- Cards: Rounded corners (12-20px), glass background, subtle shadows\n- Buttons: Pill-shaped with glass effect, hover states with luminosity changes\n- Modals: Center-floating with animated backdrop blur\n- Forms: Floating labels, glass input fields with focus glow\n- Lists/Tables: Alternating transparency, hover lift animations\n\nVisual Effects:\n- Parallax scrolling for depth perception\n- Micro-interactions on all interactive elements (scale, glow, elevation changes)\n- Smooth page transitions with shared element animations\n- Dynamic light source simulation (pseudo-elements for highlights)\n- Gradient overlays with noise texture for organic feel\n\nPerformance Optimizations:\n- Use CSS containment for animation layers\n- GPU acceleration via transform3d and will-change\n- Lazy load animation libraries\n- Optimize backdrop-filter usage (known performance cost)\n- Implement reduced motion media queries for accessibility\n\nResponsive Design:\n- Breakpoints: Mobile (< 768px), Tablet (768-1024px), Desktop (> 1024px)\n- Adapt glass intensity based on screen size\n- Simplified effects on mobile for performance\n\nBrowser Compatibility:\n- Fallbacks for backdrop-filter (solid backgrounds with opacity)\n- Prefixed CSS properties (-webkit-backdrop-filter)\n- Polyfills for older browsers or graceful degradation\n\nAssets Required:\n- Reference screenshots/videos from Apple Liquid Glass 2026 design\n- Icon set matching Apple SF Symbols style\n- High-resolution background images/gradients\n- Noise textures for glass effect authenticity\n\nTesting:\n- Visual regression testing across browsers\n- Performance metrics (FPS, paint times)\n- Accessibility audit (contrast ratios with transparency)\n- Dark mode parity verification\n\n---\n\n## Task Description\n\nCreate Dashboard with Liquid Glass 2026 Design Aesthetic\n\nRedesign the dashboard interface to match the \"Liquid Glass 2026\" visual design style, featuring modern glassmorphism effects, fluid animations, and contemporary UI patterns.\n\nRequirements:\n- Research and identify the specific Liquid Glass 2026 design characteristics (frosted glass effects, translucent layers, depth shadows, blur effects)\n- Update color scheme to match Liquid Glass 2026 palette (typically featuring soft gradients, semi-transparent backgrounds, light borders)\n- Implement glassmorphism CSS properties: backdrop-filter, background blur, opacity layers, and subtle borders\n- Add smooth, fluid animations and transitions between states\n- Update typography to match the modern, clean aesthetic of Liquid Glass 2026\n- Ensure component spacing, padding, and layout proportions align with the reference design\n- Maintain or improve accessibility standards (sufficient contrast despite transparency effects)\n- Verify responsive behavior across different screen sizes\n- Test performance impact of visual effects and optimize if necessary\n\nVisual Elements to Include:\n- Frosted glass card containers with blur effects\n- Floating elements with subtle drop shadows\n- Gradient overlays and color transitions\n- Smooth hover and interaction animations\n- Modern iconography consistent with the design language",
      "timestamp": "2026-01-17T14:16:37.800Z",
      "source": "initial"
    }
  ],
  "startedAt": "2026-01-17T14:16:45.378Z",
  "updatedAt": "2026-01-17T14:35:54.290Z"
}